pyjigsaw/__init__.py
pyjigsaw/jigsawfactory.py
pyjigsaw-0.1.1.dist-info/licenses/LICENSE
pyjigsaw-0.1.1.dist-info/METADATA
pyjigsaw-0.1.1.dist-info/WHEEL
pyjigsaw-0.1.1.dist-info/top_level.txt
pyjigsaw-0.1.1.dist-info/RECORD
