Metadata-Version: 2.4
Name: pyjigsaw
Version: 0.1.1
Summary: Package defined to create jigsaw puzzle cut templates, and digital puzzle sets.
Author-email: Tom DeAbreu <tomdeabreu@proton.me>
Project-URL: Homepage, https://github.com/tomdeabreucodes/PyJig
Project-URL: Issues, https://github.com/tomdeabreucodes/PyJig/issues
Classifier: Programming Language :: Python :: 3
Classifier: License :: OSI Approved :: MIT License
Classifier: Operating System :: POSIX :: Linux
Requires-Python: >=3.8
License-File: LICENSE
Requires-Dist: defusedxml>=0.7.1
Requires-Dist: opencv_contrib_python>=4.7.0.72
Requires-Dist: Pillow>=10.1.0
Requires-Dist: svgpathtools>=1.6.0
Dynamic: license-file
